YGueJ.v
// GUERRA, Jose Maria Angelo C. (S17)

`timescale 1ns / 1ps

/*
    Structural Modeling
    Structural Function: 2x4 Positive Output, Positive Enable Decoder
    Boolean Function: F = A (CD + B) + BC'
*/

module dec_2x4_behav(i[0], i[1], en, m[0], m[1], m[2], m[3]);
    // Define input and output
    output reg [0:3] m;
    input [0:1] i;
    input en;
	
	// Define decoder structure
	always @*
    begin
		if(en) // en = 1 : the decoder will be enabled
            begin
                m[0] = ~i[0] & ~i[1]; // 00
                m[1] = ~i[0] & i[1]; // 01
                m[2] = i[0] & ~i[1]; // 10
                m[3] = i[0] & i[1]; // 11
		    end
		else // en = 0 : the decoder will be disabled
             // values will be set to 0 as default
			{m[0], m[1], m[2], m[3]} = 4'b0000;
	end
endmodule

/*
    Sum of Minterm of Boolean Function:
    S_m = {4,5,11,12,13,14,15}
*/
module som_dec_2x4_pope_behav(F,A,B,C,D,E);
    // Define input and output
    output reg F;
    input A,B,C,D,E;
	
    // Define decoder structure
    wire [0:3] d; // Minterms 0-3 for Decoders 1-4
                  // Decoders 1-4 for inputs C and D
	wire [0:15] m; // Minterms 0-15
	
    // Call and assign decoder functions
    dec_2x4_behav D0(A, B, E, d[0], d[1], d[2], d[3]); // Decoder 0 for inputs A and B
	dec_2x4_behav D1(C, D, d[0], m[0], m[1], m[2], m[3]); // Decoder 1
	dec_2x4_behav D2(C, D, d[1], m[4], m[5], m[6], m[7]); // Decoder 2
	dec_2x4_behav D3(C, D, d[2], m[8], m[9], m[10], m[11]); // Decoder 3
	dec_2x4_behav D4(C, D, d[3], m[12], m[13], m[14], m[15]); // Decoder 4

	// Assign output based on Sum of Minterms
    always @*
    begin
		if(E) // If en = 1, decoder is enabled
            F = m[4] | m[5] | m[11] | m[12] | m[13] | m[14] | m[15];
		else // en = 0, decoder is disabled (high-impedance)
            F = 1'bZ;
	end
	
endmodule

YGueJ_tb.v
// GUERRA, Jose Maria Angelo C. (S17)

`timescale 1ns / 1ps

/*
    Structural Modeling
    Structural Function: 2x4 Positive Output, Positive Enable Decoder
    Boolean Function: F = A (CD + B) + BC'
*/

module som_dec_2x4_pope_behav_tb();

    // Declare local reg and wire identifiers
    reg[3:0] t_input;
    reg t_E;
    wire t_F;
    integer i;

    // Instantiate the design module under test
    som_dec_2x4_pope_behav dut(t_F, t_input[3], t_input[2], t_input[1], t_input[0],t_E);

    // Generate stimulus using initial statements
    initial
        begin
            // Enable = 0 (Negative)
            t_input = 4'b0000;
            t_E = 0;
            for(i = 1; i <= 17; i++)
                #10 t_input = i; // Every 10ns, value 0000 becomes 0001 and so on until it goes back to 0000
            
            $display(""); // line break

            // Enable = 1 (Positive)
            t_input = 4'b0000;
            t_E = 1;
            for(i = 1; i < 17; i++)
                #10 t_input = i; // Every 10ns, value 0000 becomes 0001 and so on until it goes back to 0000
        end

    // Display the output response (text or graphics (or both))
    initial
    begin
        $display("Written by Jose Maria Angelo Guerra (S17)");
        $display("F = A (CD + B) + BC'");
        $display("2x4 Positive Output, Positive Enable Decoder");

        $monitor("Time = %03d | A = %b B = %b C = %b D = %b | en = %b | F = %b",
                 $time, t_input[3], t_input[2], t_input[1], t_input[0], t_E, t_F);
        $dumpfile("YGueJ_dump.vcd");
        $dumpvars();
    end

endmodule

YGueJ_dump.vcd
$date
	Fri Jul 21 18:04:49 2023
$end
$version
	Icarus Verilog
$end
$timescale
	1ps
$end
$scope module som_dec_2x4_pope_behav_tb $end
$var wire 1 ! t_F $end
$var reg 1 " t_E $end
$var reg 4 # t_input [3:0] $end
$var integer 32 $ i [31:0] $end
$scope module dut $end
$var wire 1 % A $end
$var wire 1 & B $end
$var wire 1 ' C $end
$var wire 1 ( D $end
$var wire 1 " E $end
$var wire 16 ) m [0:15] $end
$var wire 4 * d [0:3] $end
$var reg 1 ! F $end
$scope module D0 $end
$var wire 1 " en $end
$var wire 2 + i [0:1] $end
$var reg 4 , m [0:3] $end
$upscope $end
$scope module D1 $end
$var wire 1 - en $end
$var wire 2 . i [0:1] $end
$var reg 4 / m [0:3] $end
$upscope $end
$scope module D2 $end
$var wire 1 0 en $end
$var wire 2 1 i [0:1] $end
$var reg 4 2 m [0:3] $end
$upscope $end
$scope module D3 $end
$var wire 1 3 en $end
$var wire 2 4 i [0:1] $end
$var reg 4 5 m [0:3] $end
$upscope $end
$scope module D4 $end
$var wire 1 6 en $end
$var wire 2 7 i [0:1] $end
$var reg 4 8 m [0:3] $end
$upscope $end
$upscope $end
$upscope $end
$enddefinitions $end
#0
$dumpvars
b0 8
b0 7
06
b0 5
b0 4
03
b0 2
b0 1
00
b0 /
b0 .
0-
b0 ,
b0 +
b0 *
b0 )
0(
0'
0&
0%
b1 $
b0 #
0"
z!
$end
#10000
b1 .
b1 1
b1 4
b1 7
1(
b10 $
b1 #
#20000
1'
b10 .
b10 1
b10 4
b10 7
0(
b11 $
b10 #
#30000
b11 .
b11 1
b11 4
b11 7
1(
b100 $
b11 #
#40000
b1 +
1&
0'
b0 .
b0 1
b0 4
b0 7
0(
b101 $
b100 #
#50000
b1 .
b1 1
b1 4
b1 7
1(
b110 $
b101 #
#60000
1'
b10 .
b10 1
b10 4
b10 7
0(
b111 $
b110 #
#70000
b11 .
b11 1
b11 4
b11 7
1(
b1000 $
b111 #
#80000
1%
b10 +
0&
0'
b0 .
b0 1
b0 4
b0 7
0(
b1001 $
b1000 #
#90000
b1 .
b1 1
b1 4
b1 7
1(
b1010 $
b1001 #
#100000
1'
b10 .
b10 1
b10 4
b10 7
0(
b1011 $
b1010 #
#110000
b11 .
b11 1
b11 4
b11 7
1(
b1100 $
b1011 #
#120000
b11 +
1&
0'
b0 .
b0 1
b0 4
b0 7
0(
b1101 $
b1100 #
#130000
b1 .
b1 1
b1 4
b1 7
1(
b1110 $
b1101 #
#140000
1'
b10 .
b10 1
b10 4
b10 7
0(
b1111 $
b1110 #
#150000
b11 .
b11 1
b11 4
b11 7
1(
b10000 $
b1111 #
#160000
0%
b0 +
0&
0'
b0 .
b0 1
b0 4
b0 7
0(
b10001 $
b0 #
#170000
b1000000000000000 )
b1000 /
1-
b1000 *
b1000 ,
0!
1"
b1 $
b0 #
#180000
b100000000000000 )
b100 /
b1 .
b1 1
b1 4
b1 7
1(
b10 $
b1 #
#190000
b10000000000000 )
b10 /
1'
b10 .
b10 1
b10 4
b10 7
0(
b11 $
b10 #
#200000
b1000000000000 )
b1 /
b11 .
b11 1
b11 4
b11 7
1(
b100 $
b11 #
#210000
1!
b1000 2
10
0-
b100 *
b100000000000 )
b100 ,
b0 /
b1 +
1&
0'
b0 .
b0 1
b0 4
b0 7
0(
b101 $
b100 #
#220000
b10000000000 )
b100 2
b1 .
b1 1
b1 4
b1 7
1(
b110 $
b101 #
#230000
0!
b1000000000 )
b10 2
1'
b10 .
b10 1
b10 4
b10 7
0(
b111 $
b110 #
#240000
b100000000 )
b1 2
b11 .
b11 1
b11 4
b11 7
1(
b1000 $
b111 #
#250000
b1000 5
13
00
0!
b10 *
b10000000 )
b10 ,
b0 2
1%
b10 +
0&
0'
b0 .
b0 1
b0 4
b0 7
0(
b1001 $
b1000 #
#260000
b1000000 )
b100 5
b1 .
b1 1
b1 4
b1 7
1(
b1010 $
b1001 #
#270000
b100000 )
b10 5
1'
b10 .
b10 1
b10 4
b10 7
0(
b1011 $
b1010 #
#280000
1!
b10000 )
b1 5
b11 .
b11 1
b11 4
b11 7
1(
b1100 $
b1011 #
#290000
b1000 8
16
03
1!
b1 *
b1000 )
b1 ,
b0 5
b11 +
1&
0'
b0 .
b0 1
b0 4
b0 7
0(
b1101 $
b1100 #
#300000
b100 )
b100 8
b1 .
b1 1
b1 4
b1 7
1(
b1110 $
b1101 #
#310000
b10 )
b10 8
1'
b10 .
b10 1
b10 4
b10 7
0(
b1111 $
b1110 #
#320000
b1 )
b1 8
b11 .
b11 1
b11 4
b11 7
1(
b10000 $
b1111 #
#330000
0!
b1000 /
06
1-
b1000 *
b1000000000000000 )
b1000 ,
b0 8
0%
b0 +
0&
0'
b0 .
b0 1
b0 4
b0 7
0(
b10001 $
b0 #
